omniblack/screen/IdDict.py
omniblack/screen/LoggingDisplay.py
omniblack/screen/MonitoredDeque.py
omniblack/screen/Process.py
omniblack/screen/__init__.py
omniblack/screen/ansi_widget.py
omniblack/screen/translate_text.py
omniblack/screen/ui.py
omniblack.screen-0.0.1.post1.dist-info/WHEEL
omniblack.screen-0.0.1.post1.dist-info/METADATA
omniblack.screen-0.0.1.post1.dist-info/RECORD
